industrialucn/__init__.py
industrialucn/econstraint.py
industrialucn/econstraint_test.py
industrialucn/experimental/__init__.py
industrialucn/experimental/osrm.py
industrialucn-0.1.7.2.dist-info/LICENSE
industrialucn-0.1.7.2.dist-info/METADATA
industrialucn-0.1.7.2.dist-info/WHEEL
industrialucn-0.1.7.2.dist-info/top_level.txt
industrialucn-0.1.7.2.dist-info/RECORD
